<annotation>
	<folder>resized_image</folder>
	<filename>DJI_0255.JPG</filename>
	<path>C:\Users\Joel7\Desktop\resized_image\DJI_0255.JPG</path>
	<source>
		<database>Unknown</database>
	</source>
	<size>
		<width>496</width>
		<height>372</height>
		<depth>3</depth>
	</size>
	<segmented>0</segmented>
	<object>
		<name>can</name>
		<pose>Unspecified</pose>
		<truncated>0</truncated>
		<difficult>0</difficult>
		<bndbox>
			<xmin>367</xmin>
			<ymin>261</ymin>
			<xmax>389</xmax>
			<ymax>277</ymax>
		</bndbox>
	</object>
	<object>
		<name>bottle</name>
		<pose>Unspecified</pose>
		<truncated>0</truncated>
		<difficult>0</difficult>
		<bndbox>
			<xmin>378</xmin>
			<ymin>343</ymin>
			<xmax>406</xmax>
			<ymax>363</ymax>
		</bndbox>
	</object>
</annotation>
